HiTech_STT/__init__.py
HiTech_STT-0.1.dist-info/METADATA
HiTech_STT-0.1.dist-info/WHEEL
HiTech_STT-0.1.dist-info/top_level.txt
HiTech_STT-0.1.dist-info/RECORD
