Metadata-Version: 2.1
Name: HiTech-STT
Version: 0.1
Summary: This is Speech To Text package created by Priyanshu Pal
Author: Priyanshu Pal
Author-email: samarendranathpal46@gmail.com
